fastapi_tools/bootstrap/__init__.py
fastapi_tools/bootstrap/model.py
fastapi_tools/bootstrap/py.typed
fastapi_tools_bootstrap-0.1.5.dist-info/METADATA
fastapi_tools_bootstrap-0.1.5.dist-info/WHEEL
fastapi_tools_bootstrap-0.1.5.dist-info/RECORD
