Metadata-Version: 2.3
Name: fastapi-tools-bootstrap
Version: 0.1.5
Summary: Bootstrap tool
Author: Andrei Churin
Author-email: aachurin@gmail.com
Requires-Python: >=3.12,<4.0
Classifier: Programming Language :: Python :: 3
Classifier: Programming Language :: Python :: 3.12
Classifier: Programming Language :: Python :: 3.13
